tm_eval/__init__.py
tm_eval/topic_modeling.py
tm_eval/__pycache__/__init__.cpython-39.pyc
tm_eval/__pycache__/topic_modeling.cpython-39.pyc
tm_eval-0.0.2.dist-info/LICENSE
tm_eval-0.0.2.dist-info/METADATA
tm_eval-0.0.2.dist-info/WHEEL
tm_eval-0.0.2.dist-info/top_level.txt
tm_eval-0.0.2.dist-info/RECORD
